sources_1/new/apple.v
`timescale 1ns / 1ps
//////////////////////////////////////////////////////////////////////////////////
// Company: 
// Engineer: 
// 
// Create Date: 2025/06/02 13:52:45
// Design Name: 
// Module Name: apple
// Project Name: 
// Target Devices: 
// Tool Versions: 
// Description: 
// 
// Dependencies: 
// 
// Revision:
// Revision 0.01 - File Created
// Additional Comments:
// 
//////////////////////////////////////////////////////////////////////////////////


module apple (
    input clk,
    input reset, 
    input [9:0]snake_x,//蛇头x
    input [9:0]snake_y,//蛇头y
    output reg [9:0] apple_x,//苹果x坐标
    output reg [9:0] apple_y,//苹果y坐标
    output reg add//判定为可加分
);
    reg [9:0] random_x; //随机数x
    reg [9:0] random_y; //随机数y,有待根据屏幕尺寸修改
    reg [15:0] lfsr;

always @(posedge clk or posedge reset) begin
    if (reset)
        lfsr <= 16'hACE1; // 初始种子
    else
        lfsr <= {lfsr[14:0], lfsr[15] ^ lfsr[13] ^ lfsr[12] ^ lfsr[10]};
        random_x <= lfsr[9:0];
        random_y <= lfsr[15:6];
end



always @(posedge clk or posedge reset) begin
    if (reset) begin
        apple_x <= 10'd16; // Reset 
        apple_y <= 10'd20; // Reset 
        add <= 1'b0; // Reset add signal
    end else begin
        if (snake_x == apple_x && snake_y == apple_y) begin
            add <= 1'b1; 
            apple_x <= random_x[9:0]; // Update apple_x with random value
            apple_y <= random_y[9:0]; // Update apple_y with random value
        end else begin
            add <= 1'b0; // No collision, reset add signal
        end
    end
end
endmodule

Final Project.srcs/sources_1/new/snake.v
module snake_direction (
    input clk,
    input reset, //低电平有效
    input [3:0] BTN, //方向选择输入
    input [1:0] SW, //难度输入
    output reg [9:0] head_x, //蛇头位置
    output reg [9:0] head_y, //蛇头位置

    input [1:0] game_state, // 游戏状态
    input add, // 蛇长度增长
    output reg hit_wall, // 碰撞墙壁
    output reg hit_self  // 碰撞自身
);

localparam UP    = 4'b0001;
localparam DOWN  = 4'b0010;
localparam LEFT  = 4'b0100;
localparam RIGHT = 4'b1000;

localparam MAX_X = 10'd640;//有待修改
localparam MAX_Y = 10'd480;

localparam STATE_START   = 2'b00;
localparam STATE_RESTART = 2'b01;
localparam STATE_OVER    = 2'b10;
localparam STATE_PLAYING = 2'b11;

reg [9:0] node_x [0:15];
reg [9:0] node_y [0:15];
reg [3:0] length; // 最大长度16
reg [31:0] counter;
reg [31:0] speed;
reg [3:0] direction;
reg debug;

// 速度设定
always @(posedge clk or negedge reset) begin
    if (!reset) begin
        speed <= 32'd500000;
    end else begin
        case (SW[1:0])
            2'b01: speed <= 32'd500000;
            2'b10: speed <= 32'd1000000;
            2'b11: speed <= 32'd1500000;
            default: speed <= 32'd500000;
        endcase
    end
end

// 方向控制
always @(posedge clk or negedge reset) begin
    if (!reset) direction <= RIGHT;
    else begin
        case (BTN)
            UP:    if (direction != DOWN)  direction <= UP;
            DOWN:  if (direction != UP)    direction <= DOWN;
            LEFT:  if (direction != RIGHT) direction <= LEFT;
            RIGHT: if (direction != LEFT)  direction <= RIGHT;
            default: direction <= direction;
        endcase
    end
end

// 初始化/移动逻辑
integer i;
always @(posedge clk or negedge reset) begin
    if (!reset || game_state == STATE_RESTART) begin
        length <= 4'd3;
        node_x[0] <= 10'd16; node_y[0] <= 10'd16;
        node_x[1] <= 10'd15; node_y[1] <= 10'd16;
        node_x[2] <= 10'd14; node_y[2] <= 10'd16;
        for (i = 3; i < 16; i = i + 1) begin
            node_x[i] <= 10'd0;
            node_y[i] <= 10'd0;
        end
        direction <= RIGHT;
        hit_wall <= 1'b0;
        hit_self <= 1'b0;
    end else begin
        debug<=1;
        counter <= counter + 1;
        if (counter >= (debug)?debug:speed && game_state == STATE_PLAYING) begin
            counter <= 0;

            // 撞墙检测
            if ((node_x[0] == MAX_X && direction == RIGHT) ||
                (node_x[0] == 0 && direction == LEFT) ||
                (node_y[0] == MAX_Y && direction == DOWN) ||
                (node_y[0] == 0 && direction == UP)) begin
                hit_wall <= 1'b1;
            end else begin
                hit_wall <= 1'b0;

                // 撞自己检测
                hit_self <= 1'b0;
                for (i = 1; i < length; i = i + 1) begin
                    if (node_x[0] == node_x[i] && node_y[0] == node_y[i]) begin
                        hit_self <= 1'b1;
                    end
                end

                // 蛇移动
                if (!hit_self) begin
                    if (length < 15) begin
                        node_x[length + 1] <= node_x[length];
                        node_y[length + 1] <= node_y[length];
                    end

                    for (i = length; i > 0; i = i - 1) begin
                        node_x[i] <= node_x[i - 1];
                        node_y[i] <= node_y[i - 1];
                    end

                    case (direction)
                        UP:    node_y[0] <= node_y[0] - 1;
                        DOWN:  node_y[0] <= node_y[0] + 1;
                        LEFT:  node_x[0] <= node_x[0] - 1;
                        RIGHT: node_x[0] <= node_x[0] + 1;
                        default: ;
                    endcase

                    if (add && length < 15) begin
                        length <= length + 1;
                    end
                end
            end
        end
    end
    head_x <= node_x[0];
    head_y <= node_y[0];
end

endmodule

sources_1/new/game.v
module game(
    input clk,
    input reset,//低电平有效
    input [3:0] BTN,
    input [2:0] SW,
    input hit_wall, //碰撞墙壁
    input hit_self, //碰撞自身
    output reg [1:0]  game_state//游戏状态
);
    // 游戏状态定义
    localparam STATE_START = 2'b00; // 游戏开始
    localparam STATE_PAUSE= 2'b01; // 重新开始
    localparam STATE_OVER = 2'b10; // 游戏结束
    localparam STATE_PLAYING = 2'b11; // 游戏进行中
    //reg [32:0] counter; //计数器
    always@(posedge clk or negedge reset) begin
        if (reset) begin
            //counter <= 0;
            game_state <= STATE_START; // 初始化游戏状态为开始
            end
        else begin
            case(game_state)
                STATE_START: begin
                    if (SW[0] || SW[1] || SW[2]) begin
                        game_state <= STATE_PLAYING; // 按下任意难度选择开关，进入游戏进行状态
                        //counter <= 0; // 重置计数器
                    end else begin
                        game_state <= STATE_START; // 保持在开始状态
                    end               
                end

                STATE_PAUSE: begin
                    if (BTN[0] | BTN[1] |BTN[2]|BTN[3]) begin
                        game_state <= STATE_PLAYING; // 按下任意方向开关，进入游戏进行状态
                        //counter <= 0; // 重置计数器
                    end else begin
                        game_state <= STATE_PAUSE; // 保持在暂停状态
                    end
                end

                STATE_PLAYING: begin
                    if (hit_wall || hit_self) begin
                        game_state <= STATE_OVER; // 碰撞墙壁或自身，进入游戏结束状态
                    end else begin
                        game_state <= STATE_PLAYING; // 保持在游戏进行状态
                    end
                end
                STATE_OVER: begin
                    if (BTN[0] || BTN[1] || BTN[2] ||BTN[3]) begin
                        game_state <= STATE_START; // 按下任意按钮，进入开始状态
                        //counter <= 0; // 重置计数器
                    end else begin
                        game_state <= STATE_OVER; // 保持在游戏结束状态
                    end
                end
                default: begin
                    game_state <= STATE_START; // 默认状态为开始
                end
            endcase
        end
    end
endmodule

sources_1/new/scores.v
module scores (
    input  clk,
    input  reset, 
    input  add,//判定为可加分
    //input [1:0] game_state, //游戏状态
    output reg [11:0] score//当前分数
);
always @(posedge clk or posedge  reset) begin
    if (reset) begin
        score <= 0; // Reset score to 0
    end else if (add) begin
        if (score < 12'b1111_1111_1111) begin // Check if score is less than the maximum value (4095)
            score <= score + 1; // Increment score by 1
        end
        end
    end
endmodule //scores

Final Project.srcs/sources_1/new/top.v
module top(
    input clk,
    input reset, //低电平有效
    input [3:0] BTN, //方向选择输入
    input [2:0] SW,  //难度输入
    output [9:0] head_x,
    output [9:0] head_y,
    output [11:0] score
);
    wire add;
    wire [9:0] apple_x;
    wire [9:0] apple_y;
    wire hit_wall;
    wire hit_self;
    wire [1:0] game_state;

    scores scores_inst (
        .clk(clk),
        .reset(reset),
        .add(add),
        .score(score)
    );

    game game_inst (
        .clk(clk),
        .reset(reset),
        .BTN(BTN),
        .SW(SW),
        .hit_wall(hit_wall),
        .hit_self(hit_self),
        .game_state(game_state)
    );

    snake_direction snake_direction_inst (
        .clk(clk),
        .reset(reset),
        .BTN(BTN),
        .SW(SW),
        .head_x(head_x),
        .head_y(head_y),
        .game_state(game_state),
        .add(add),
        .hit_wall(hit_wall),
        .hit_self(hit_self)
    );

    apple apple_inst (
        .clk(clk),
        .reset(reset),
        .snake_x(head_x),
        .snake_y(head_y),
        .apple_x(apple_x),
        .apple_y(apple_y),
        .add(add)
    );
endmodule

sim_1/new/top_tb.v
`timescale 1ns / 1ps

module top_tb;
    reg clk;
    reg reset;
    reg [3:0] BTN;
    reg [2:0] SW;
    
    wire [9:0] head_x;
    wire [9:0] head_y;
    wire [11:0] score;

    // 实例化 top 模块
    top uut (
        .clk(clk),
        .reset(reset),
        .BTN(BTN),
        .SW(SW),
        .head_x(head_x),
        .head_y(head_y),
        .score(score)
    );

    // 产生时钟信号
    initial begin
        clk = 0;
        forever #5 clk = ~clk; // 100MHz 时钟
    end

    // 主测试逻辑
    initial begin
        $display("Simulation Start");
        $dumpfile("top_tb.vcd");
        $dumpvars(0, top_tb);

        // 初始化
        reset = 0;
        BTN = 4'b0000;
        SW = 3'b001; // 设置初始速度
        #20;

        reset = 1; // 释放复位
        #50;

        // 模拟按键按下（向右）


        // 模拟向下
        BTN = 4'b0010;
        #200;

        // 模拟吃苹果或蛇移动情况
        BTN = 4'b0001;
        #500;

        // 模拟长时间运行
        BTN = 4'b0000;
        #2000;

        // 结束仿真
        $display("Simulation End");
        $finish;
    end
endmodule

Final Project.sim/sim_1/behav/xsim/top_tb.vcd
$date
   Mon Jun  2 16:43:53 2025
$end
$version
  2022.2
$end
$timescale
  1ps
$end
$scope module top_tb $end
$var reg 1 ! clk $end
$var reg 1 " reset $end
$var reg 4 # BTN [3:0] $end
$var reg 3 $ SW [2:0] $end
$var wire 10 % head_x [9:0] $end
$var wire 10 & head_y [9:0] $end
$var wire 12 ' score [11:0] $end
$scope module uut $end
$var wire 1 ( clk $end
$var wire 1 ) reset $end
$var wire 4 * BTN [3:0] $end
$var wire 3 + SW [2:0] $end
$var wire 10 % head_x [9:0] $end
$var wire 10 & head_y [9:0] $end
$var wire 12 ' score [11:0] $end
$var wire 1 , add $end
$var wire 10 - apple_x [9:0] $end
$var wire 10 . apple_y [9:0] $end
$var wire 1 / hit_wall $end
$var wire 1 0 hit_self $end
$var wire 2 1 game_state [1:0] $end
$scope module scores_inst $end
$var wire 1 ( clk $end
$var wire 1 ) reset $end
$var wire 1 , add $end
$var reg 12 2 score [11:0] $end
$upscope $end
$scope module game_inst $end
$var wire 1 ( clk $end
$var wire 1 ) reset $end
$var wire 4 * BTN [3:0] $end
$var wire 3 + SW [2:0] $end
$var wire 1 / hit_wall $end
$var wire 1 0 hit_self $end
$var reg 2 3 game_state [1:0] $end
$upscope $end
$scope module snake_direction_inst $end
$var wire 1 ( clk $end
$var wire 1 ) reset $end
$var wire 4 * BTN [3:0] $end
$var wire 2 4 SW [1:0] $end
$var reg 10 5 head_x [9:0] $end
$var reg 10 6 head_y [9:0] $end
$var wire 2 1 game_state [1:0] $end
$var wire 1 , add $end
$var reg 1 7 hit_wall $end
$var reg 1 8 hit_self $end
$var reg 4 9 length [3:0] $end
$var reg 32 : counter [31:0] $end
$var reg 32 ; speed [31:0] $end
$var reg 4 < direction [3:0] $end
$var reg 1 = debug $end
$var integer 32 > i [31:0] $end
$upscope $end
$scope module apple_inst $end
$var wire 1 ( clk $end
$var wire 1 ) reset $end
$var wire 10 % snake_x [9:0] $end
$var wire 10 & snake_y [9:0] $end
$var reg 10 ? apple_x [9:0] $end
$var reg 10 @ apple_y [9:0] $end
$var reg 1 A add $end
$var reg 10 B random_x [9:0] $end
$var reg 10 C random_y [9:0] $end
$var reg 16 D lfsr [15:0] $end
$upscope $end
$upscope $end
$upscope $end
$enddefinitions $end
#0
$dumpvars
0!
0"
b0 #
b1 $
bx %
bx &
b0 '
0(
0)
b0 *
b1 +
0,
b10000 -
b10100 .
0/
00
b0 1
b0 2
b0 3
b1 4
bx 5
bx 6
07
08
b11 9
bx :
b1111010000100100000 ;
b1000 <
x=
bx >
b10000 ?
b10100 @
0A
bx B
bx C
b1010110011100001 D
$end
#5000
1!
b10000 %
b10000 &
1(
b10000 5
b10000 6
b11100001 B
b1010110011 C
#10000
0!
0(
#15000
1!
1(
#20000
0!
1"
0(
1)
#25000
1!
1(
1=
b101100111000011 D
#30000
0!
0(
#35000
1!
1(
b111000011 B
b101100111 C
b1011001110000111 D
#40000
0!
0(
#45000
1!
1(
b1110000111 B
b1011001110 C
b110011100001111 D
#50000
0!
0(
#55000
1!
1(
b1100001111 B
b110011100 C
b1100111000011110 D
#60000
0!
0(
#65000
1!
1(
b1000011110 B
b1100111000 C
b1001110000111100 D
#70000
0!
b10 #
0(
b10 *
#75000
1!
1(
b11 1
b11 3
b10 <
b111100 B
b1001110000 C
b11100001111001 D
#80000
0!
0(
#85000
1!
1(
b0 :
b0 >
b1111001 B
b11100001 C
b111000011110010 D
#90000
0!
0(
#95000
1!
b10001 &
1(
b10001 6
b0 :
b0 >
b11110010 B
b111000011 C
b1110000111100100 D
#100000
0!
0(
#105000
1!
b10010 &
1(
b10010 6
b0 :
b0 >
b111100100 B
b1110000111 C
b1100001111001000 D
#110000
0!
0(
#115000
1!
b10011 &
1(
b10011 6
b0 :
b0 >
b1111001000 B
b1100001111 C
b1000011110010001 D
#120000
0!
0(
#125000
1!
b10100 &
1(
b10100 6
b0 :
b0 >
b1110010001 B
b1000011110 C
b111100100010 D
#130000
0!
0(
#135000
1!
b10101 &
1(
1,
b1110010001 -
b1000011110 .
b10101 6
b0 :
b0 >
b1110010001 ?
b1000011110 @
1A
b1100100010 B
b111100 C
b1111001000101 D
#140000
0!
0(
#145000
1!
b10110 &
b1 '
1(
0,
b1 2
b10110 6
b100 9
b0 :
b0 >
0A
b1001000101 B
b1111001 C
b11110010001010 D
#150000
0!
0(
#155000
1!
b10111 &
1(
b10111 6
b0 :
b0 >
b10001010 B
b11110010 C
b111100100010101 D
#160000
0!
0(
#165000
1!
b11000 &
1(
b11000 6
b0 :
b0 >
b100010101 B
b111100100 C
b1111001000101010 D
#170000
0!
0(
#175000
1!
b11001 &
1(
b11001 6
b0 :
b0 >
b1000101010 B
b1111001000 C
b1110010001010101 D
#180000
0!
0(
#185000
1!
b11010 &
1(
b11010 6
b0 :
b0 >
b1010101 B
b1110010001 C
b1100100010101011 D
#190000
0!
0(
#195000
1!
b11011 &
1(
b11011 6
b0 :
b0 >
b10101011 B
b1100100010 C
b1001000101010111 D
#200000
0!
0(
#205000
1!
b11100 &
1(
b11100 6
b0 :
b0 >
b101010111 B
b1001000101 C
b10001010101110 D
#210000
0!
0(
#215000
1!
b11101 &
1(
b11101 6
b0 :
b0 >
b1010101110 B
b10001010 C
b100010101011101 D
#220000
0!
0(
#225000
1!
b11110 &
1(
b11110 6
b0 :
b0 >
b101011101 B
b100010101 C
b1000101010111011 D
#230000
0!
0(
#235000
1!
b11111 &
1(
b11111 6
b0 :
b0 >
b1010111011 B
b1000101010 C
b1010101110111 D
#240000
0!
0(
#245000
1!
b100000 &
1(
b100000 6
b0 :
b0 >
b101110111 B
b1010101 C
b10101011101110 D
#250000
0!
0(
#255000
1!
b100001 &
1(
b100001 6
b0 :
b0 >
b1011101110 B
b10101011 C
b101010111011101 D
#260000
0!
0(
#265000
1!
b100010 &
1(
b100010 6
b0 :
b0 >
b111011101 B
b101010111 C
b1010101110111010 D
#270000
0!
b1 #
0(
b1 *
#275000
1!
b100011 &
1(
b100011 6
b0 :
b0 >
b1110111010 B
b1010101110 C
b101011101110100 D
#280000
0!
0(
#285000
1!
b100100 &
1(
b100100 6
b0 :
b0 >
b1101110100 B
b101011101 C
b1010111011101000 D
#290000
0!
0(
#295000
1!
b100101 &
1(
b100101 6
b0 :
b0 >
b1011101000 B
b1010111011 C
b101110111010001 D
#300000
0!
0(
#305000
1!
b100110 &
1(
b100110 6
b0 :
b0 >
b111010001 B
b101110111 C
b1011101110100010 D
#310000
0!
0(
#315000
1!
b100111 &
1(
b100111 6
b0 :
b0 >
b1110100010 B
b1011101110 C
b111011101000101 D
#320000
0!
0(
#325000
1!
b101000 &
1(
b101000 6
b0 :
b0 >
b1101000101 B
b111011101 C
b1110111010001011 D
#330000
0!
0(
#335000
1!
b101001 &
1(
b101001 6
b0 :
b0 >
b1010001011 B
b1110111010 C
b1101110100010111 D
#340000
0!
0(
#345000
1!
b101010 &
1(
b101010 6
b0 :
b0 >
b100010111 B
b1101110100 C
b1011101000101111 D
#350000
0!
0(
#355000
1!
b101011 &
1(
b101011 6
b0 :
b0 >
b1000101111 B
b1011101000 C
b111010001011111 D
#360000
0!
0(
#365000
1!
b101100 &
1(
b101100 6
b0 :
b0 >
b1011111 B
b111010001 C
b1110100010111111 D
#370000
0!
0(
#375000
1!
b101101 &
1(
b101101 6
b0 :
b0 >
b10111111 B
b1110100010 C
b1101000101111110 D
#380000
0!
0(
#385000
1!
b101110 &
1(
b101110 6
b0 :
b0 >
b101111110 B
b1101000101 C
b1010001011111100 D
#390000
0!
0(
#395000
1!
b101111 &
1(
b101111 6
b0 :
b0 >
b1011111100 B
b1010001011 C
b100010111111000 D
#400000
0!
0(
#405000
1!
b110000 &
1(
b110000 6
b0 :
b0 >
b111111000 B
b100010111 C
b1000101111110001 D
#410000
0!
0(
#415000
1!
b110001 &
1(
b110001 6
b0 :
b0 >
b1111110001 B
b1000101111 C
b1011111100011 D
#420000
0!
0(
#425000
1!
b110010 &
1(
b110010 6
b0 :
b0 >
b1111100011 B
b1011111 C
b10111111000110 D
#430000
0!
0(
#435000
1!
b110011 &
1(
b110011 6
b0 :
b0 >
b1111000110 B
b10111111 C
b101111110001100 D
#440000
0!
0(
#445000
1!
b110100 &
1(
b110100 6
b0 :
b0 >
b1110001100 B
b101111110 C
b1011111100011000 D
#450000
0!
0(
#455000
1!
b110101 &
1(
b110101 6
b0 :
b0 >
b1100011000 B
b1011111100 C
b111111000110000 D
#460000
0!
0(
#465000
1!
b110110 &
1(
b110110 6
b0 :
b0 >
b1000110000 B
b111111000 C
b1111110001100001 D
#470000
0!
0(
#475000
1!
b110111 &
1(
b110111 6
b0 :
b0 >
b1100001 B
b1111110001 C
b1111100011000010 D
#480000
0!
0(
#485000
1!
b111000 &
1(
b111000 6
b0 :
b0 >
b11000010 B
b1111100011 C
b1111000110000101 D
#490000
0!
0(
#495000
1!
b111001 &
1(
b111001 6
b0 :
b0 >
b110000101 B
b1111000110 C
b1110001100001011 D
#500000
0!
0(
#505000
1!
b111010 &
1(
b111010 6
b0 :
b0 >
b1100001011 B
b1110001100 C
b1100011000010110 D
#510000
0!
0(
#515000
1!
b111011 &
1(
b111011 6
b0 :
b0 >
b1000010110 B
b1100011000 C
b1000110000101100 D
#520000
0!
0(
#525000
1!
b111100 &
1(
b111100 6
b0 :
b0 >
b101100 B
b1000110000 C
b1100001011000 D
#530000
0!
0(
#535000
1!
b111101 &
1(
b111101 6
b0 :
b0 >
b1011000 B
b1100001 C
b11000010110001 D
#540000
0!
0(
#545000
1!
b111110 &
1(
b111110 6
b0 :
b0 >
b10110001 B
b11000010 C
b110000101100010 D
#550000
0!
0(
#555000
1!
b111111 &
1(
b111111 6
b0 :
b0 >
b101100010 B
b110000101 C
b1100001011000101 D
#560000
0!
0(
#565000
1!
b1000000 &
1(
b1000000 6
b0 :
b0 >
b1011000101 B
b1100001011 C
b1000010110001011 D
#570000
0!
0(
#575000
1!
b1000001 &
1(
b1000001 6
b0 :
b0 >
b110001011 B
b1000010110 C
b101100010110 D
#580000
0!
0(
#585000
1!
b1000010 &
1(
b1000010 6
b0 :
b0 >
b1100010110 B
b101100 C
b1011000101100 D
#590000
0!
0(
#595000
1!
b1000011 &
1(
b1000011 6
b0 :
b0 >
b1000101100 B
b1011000 C
b10110001011000 D
#600000
0!
0(
#605000
1!
b1000100 &
1(
b1000100 6
b0 :
b0 >
b1011000 B
b10110001 C
b101100010110000 D
#610000
0!
0(
#615000
1!
b1000101 &
1(
b1000101 6
b0 :
b0 >
b10110000 B
b101100010 C
b1011000101100001 D
#620000
0!
0(
#625000
1!
b1000110 &
1(
b1000110 6
b0 :
b0 >
b101100001 B
b1011000101 C
b110001011000011 D
#630000
0!
0(
#635000
1!
b1000111 &
1(
b1000111 6
b0 :
b0 >
b1011000011 B
b110001011 C
b1100010110000111 D
#640000
0!
0(
#645000
1!
b1001000 &
1(
b1001000 6
b0 :
b0 >
b110000111 B
b1100010110 C
b1000101100001110 D
#650000
0!
0(
#655000
1!
b1001001 &
1(
b1001001 6
b0 :
b0 >
b1100001110 B
b1000101100 C
b1011000011101 D
#660000
0!
0(
#665000
1!
b1001010 &
1(
b1001010 6
b0 :
b0 >
b1000011101 B
b1011000 C
b10110000111010 D
#670000
0!
0(
#675000
1!
b1001011 &
1(
b1001011 6
b0 :
b0 >
b111010 B
b10110000 C
b101100001110100 D
#680000
0!
0(
#685000
1!
b1001100 &
1(
b1001100 6
b0 :
b0 >
b1110100 B
b101100001 C
b1011000011101001 D
#690000
0!
0(
#695000
1!
b1001101 &
1(
b1001101 6
b0 :
b0 >
b11101001 B
b1011000011 C
b110000111010011 D
#700000
0!
0(
#705000
1!
b1001110 &
1(
b1001110 6
b0 :
b0 >
b111010011 B
b110000111 C
b1100001110100111 D
#710000
0!
0(
#715000
1!
b1001111 &
1(
b1001111 6
b0 :
b0 >
b1110100111 B
b1100001110 C
b1000011101001111 D
#720000
0!
0(
#725000
1!
b1010000 &
1(
b1010000 6
b0 :
b0 >
b1101001111 B
b1000011101 C
b111010011110 D
#730000
0!
0(
#735000
1!
b1010001 &
1(
b1010001 6
b0 :
b0 >
b1010011110 B
b111010 C
b1110100111101 D
#740000
0!
0(
#745000
1!
b1010010 &
1(
b1010010 6
b0 :
b0 >
b100111101 B
b1110100 C
b11101001111010 D
#750000
0!
0(
#755000
1!
b1010011 &
1(
b1010011 6
b0 :
b0 >
b1001111010 B
b11101001 C
b111010011110100 D
#760000
0!
0(
#765000
1!
b1010100 &
1(
b1010100 6
b0 :
b0 >
b11110100 B
b111010011 C
b1110100111101001 D
#770000
0!
b0 #
0(
b0 *
#775000
1!
b1010101 &
1(
b1010101 6
b0 :
b0 >
b111101001 B
b1110100111 C
b1101001111010010 D
#780000
0!
0(
#785000
1!
b1010110 &
1(
b1010110 6
b0 :
b0 >
b1111010010 B
b1101001111 C
b1010011110100100 D
#790000
0!
0(
#795000
1!
b1010111 &
1(
b1010111 6
b0 :
b0 >
b1110100100 B
b1010011110 C
b100111101001001 D
#800000
0!
0(
#805000
1!
b1011000 &
1(
b1011000 6
b0 :
b0 >
b1101001001 B
b100111101 C
b1001111010010011 D
#810000
0!
0(
#815000
1!
b1011001 &
1(
b1011001 6
b0 :
b0 >
b1010010011 B
b1001111010 C
b11110100100111 D
#820000
0!
0(
#825000
1!
b1011010 &
1(
b1011010 6
b0 :
b0 >
b100100111 B
b11110100 C
b111101001001111 D
#830000
0!
0(
#835000
1!
b1011011 &
1(
b1011011 6
b0 :
b0 >
b1001001111 B
b111101001 C
b1111010010011110 D
#840000
0!
0(
#845000
1!
b1011100 &
1(
b1011100 6
b0 :
b0 >
b10011110 B
b1111010010 C
b1110100100111100 D
#850000
0!
0(
#855000
1!
b1011101 &
1(
b1011101 6
b0 :
b0 >
b100111100 B
b1110100100 C
b1101001001111000 D
#860000
0!
0(
#865000
1!
b1011110 &
1(
b1011110 6
b0 :
b0 >
b1001111000 B
b1101001001 C
b1010010011110000 D
#870000
0!
0(
#875000
1!
b1011111 &
1(
b1011111 6
b0 :
b0 >
b11110000 B
b1010010011 C
b100100111100001 D
#880000
0!
0(
#885000
1!
b1100000 &
1(
b1100000 6
b0 :
b0 >
b111100001 B
b100100111 C
b1001001111000010 D
#890000
0!
0(
#895000
1!
b1100001 &
1(
b1100001 6
b0 :
b0 >
b1111000010 B
b1001001111 C
b10011110000100 D
#900000
0!
0(
#905000
1!
b1100010 &
1(
b1100010 6
b0 :
b0 >
b1110000100 B
b10011110 C
b100111100001000 D
#910000
0!
0(
#915000
1!
b1100011 &
1(
b1100011 6
b0 :
b0 >
b1100001000 B
b100111100 C
b1001111000010001 D
#920000
0!
0(
#925000
1!
b1100100 &
1(
b1100100 6
b0 :
b0 >
b1000010001 B
b1001111000 C
b11110000100011 D
#930000
0!
0(
#935000
1!
b1100101 &
1(
b1100101 6
b0 :
b0 >
b100011 B
b11110000 C
b111100001000111 D
#940000
0!
0(
#945000
1!
b1100110 &
1(
b1100110 6
b0 :
b0 >
b1000111 B
b111100001 C
b1111000010001110 D
#950000
0!
0(
#955000
1!
b1100111 &
1(
b1100111 6
b0 :
b0 >
b10001110 B
b1111000010 C
b1110000100011101 D
#960000
0!
0(
#965000
1!
b1101000 &
1(
b1101000 6
b0 :
b0 >
b100011101 B
b1110000100 C
b1100001000111010 D
#970000
0!
0(
#975000
1!
b1101001 &
1(
b1101001 6
b0 :
b0 >
b1000111010 B
b1100001000 C
b1000010001110101 D
#980000
0!
0(
#985000
1!
b1101010 &
1(
b1101010 6
b0 :
b0 >
b1110101 B
b1000010001 C
b100011101010 D
#990000
0!
0(
#995000
1!
b1101011 &
1(
b1101011 6
b0 :
b0 >
b11101010 B
b100011 C
b1000111010100 D
